Workbook

Sheet Read me
A1: Student Kare — full build backlog
A2: Every screen on the design canvas (StudentKare — Onboarding & Auth Flows, 239 artboards on 9 pages), split into buildable tickets. Built 29 Sep 2026.
A4: How to use
A5: • Tickets tab: one row per ticket. Edit only Status, Owner and Sprint (yellow headers).
A6: • Status: To do · In progress · In review · Done · Blocked.
A7: • Priority: P0 = needed for launch · P1 = launch month · P2 = later. Phase: 0 Foundations → 1 Launch → 2 Launch month → 3 Later.
A8: • Tier (from DESIGN.md): 1 = safety-critical, needs named design + clinical/legal review before build · 2 = core flow · 3 = composable from components.
A9: • Estimate is in story points (1, 2, 3, 5, 8) and is a first guess for planning — re-point in refinement.
A10: • Depends on: ticket IDs that should be done first. Screens: exact artboard names on the canvas (and in the screens pack).
A11: • Screens tab: every artboard → the ticket that builds it. Epics tab: totals per epic.
A12: • This replaces studentkare-engineering-backlog.xlsx: its 41 tickets are folded in (see "Replaces" column). Tickets do not check what already exists in the repo — confirm in refinement.
A13: • Jira/Linear import: use studentkare-full-backlog.csv from the same folder.
A15: Summary (updates as you edit Status)
B17: Tickets | C17: Points | D17: Done | E17: Open | F17: % done (tickets)
A18: P0 | B18: =COUNTIF(Tickets!$I$2:$I$148,A18) -> 90 | C18: =SUMIF(Tickets!$I$2:$I$148,A18,Tickets!$K$2:$K$148) -> 536 | D18: =COUNTIFS(Tickets!$I$2:$I$148,A18,Tickets!$R$2:$R$148,"Done") -> 0 | E18: =B18-D18 -> 90 | F18: =IF(B18=0,0,D18/B18) -> 0
A19: P1 | B19: =COUNTIF(Tickets!$I$2:$I$148,A19) -> 46 | C19: =SUMIF(Tickets!$I$2:$I$148,A19,Tickets!$K$2:$K$148) -> 199 | D19: =COUNTIFS(Tickets!$I$2:$I$148,A19,Tickets!$R$2:$R$148,"Done") -> 0 | E19: =B19-D19 -> 46 | F19: =IF(B19=0,0,D19/B19) -> 0
A20: P2 | B20: =COUNTIF(Tickets!$I$2:$I$148,A20) -> 11 | C20: =SUMIF(Tickets!$I$2:$I$148,A20,Tickets!$K$2:$K$148) -> 50 | D20: =COUNTIFS(Tickets!$I$2:$I$148,A20,Tickets!$R$2:$R$148,"Done") -> 0 | E20: =B20-D20 -> 11 | F20: =IF(B20=0,0,D20/B20) -> 0
A21: Total | B21: =SUM(B18:B20) -> 147 | C21: =SUM(C18:C20) -> 785 | D21: =SUM(D18:D20) -> 0 | E21: =SUM(E18:E20) -> 147 | F21: =IF(B21=0,0,D21/B21) -> 0
A23: Open decisions that block tickets
A24: • Student Plus price: ₹99 (code) or ₹199 (designs) — blocks SK-005 and pricing screens.
A25: • Under-18 accounts: AGENTS.md says 18+ only; the guardian-consent tickets need a yes/no.
A26: • D1 palette, D2 font, D3 dark mode (DESIGN.md) — blocks SK-007.
A27: • Real grievance-officer details and legal review — blocks legal pages and launch.
A28: • Named clinical reviewer for every Tier 1 ticket.

Sheet Tickets
A1: ID | B1: Epic | C1: Ticket | D1: Type | E1: Platform | F1: Screens (canvas) | G1: Canvas page | H1: Tier | I1: Priority | J1: Phase | K1: Estimate (pts) | L1: Description | M1: Acceptance criteria | N1: Depends on | O1: Depends on (names) | P1: Backend / API needed | Q1: Rules, risks & decisions | R1: Status | S1: Owner | T1: Sprint | U1: Replaces
A2: SK-001 | B2: E0 · Launch blockers | C2: Delete the fake X-ray diagnosis endpoint | D2: Task | E2: Backend | F2: — | G2: — | H2: 1 | I2: P0 | J2: 0 · Foundations | K2: 2 | L2: The /ai/xray-diagnostic-scan route returns an AI "diagnosis". Student Kare never diagnoses. Remove the route, its service and any UI that calls it (patch SK-001 already prepared). | M2: • Route removed; calling it returns 404 • No UI entry point remains • Test covers the 404 | P2: Remove route + service | Q2: No AI diagnosis anywhere in the product. | R2: To do | U2: SKB-001
A3: SK-002 | B3: E0 · Launch blockers | C3: Remove camera vitals and the fake readings they create | D3: Task | E3: Mobile + Backend | F3: Devices | G3: 2 · Student app (mobile) | H3: 1 | I3: P0 | J3: 0 · Foundations | K3: 3 | L3: Camera-based vitals (rPPG) produced invented numbers. Remove /health/camera-scan and the four camera scanner components; Devices shows only real paired devices and typed readings (patch SK-002). | M3: • Camera scan route and components deleted • No stored reading without a device or "Typed by you" source • Devices screen matches the redesigned board | P3: Remove /health/camera-scan | Q3: Honest data: no invented numbers. | R3: To do | U3: SKB-002
A4: SK-003 | B4: E0 · Launch blockers | C4: Turn demo mode off by default (no demo admin, no fixed OTP) | D4: Task | E4: Backend | F4: SignIn, OtpVerify, AdminSignIn | G4: 1 · Launch & onboarding, 7 · Super admin | H4: 1 | I4: P0 | J4: 0 · Foundations | K4: 3 | L4: Demo seeding and the console OTP must only run when APP_ENV is development/testing AND SEED_DEMO_DATA=true. Production never creates a SUPER_ADMIN demo user or accepts 123456 (patch SK-004). | M4: • Fresh production install has no admin and no demo users • OTP is random, 6 digits, 5-minute expiry, 5 tries • DEV_OTP_CONSOLE defaults to false • Tests cover both modes | P4: workflow_auth demo_mode_enabled() | R4: To do | U4: SKB-003
A5: SK-004 | B5: E0 · Launch blockers | C5: Lock the APILayer proxy endpoints behind super-admin auth | D5: Task | E5: Backend | F5: AdminApiKeys, Integrations | G5: 7 · Super admin | H5: 1 | I5: P0 | J5: 0 · Foundations | K5: 3 | L5: The 14 APILayer proxy routes are open. Require super-admin auth on the router, rotate the keys, and log each call (patch SK-005). The API access & keys screen shows key status. | M5: • Unauthenticated call returns 401 • Keys rotated and stored as secrets • Audit log entry per call (no request bodies) | N5: SK-128 | O5: Staff and admin sign-in, console home | P5: Router dependency require_super_admin | R5: To do | U5: SKB-004
A6: SK-005 | B6: E0 · Launch blockers | C6: One source of truth for the Student Plus price | D6: Task | E6: Web + Mobile + Backend | F6: AdminPriceFix, AdminPlansPricing, WebPlans, PlanBilling | G6: 7 · Super admin, 3a · Student web — public site, 2 · Student app (mobile) | H6: 1 | I6: P0 | J6: 0 · Foundations | K6: 3 | L6: Code says ₹99, designs say ₹199. Pick the price (decision), store it once, and make every surface read it. The AdminPriceFix screen lists every place a price appears (patch SK-006). | M6: • Decision recorded (₹99 or ₹199) • Price comes from one config/API value • Web Plans, Plan & billing, checkout and admin all show the same number | P6: Plans endpoint returns price in paise | Q6: Price always shown before the student commits. | R6: To do | U6: SKB-005
A7: SK-006 | B7: E0 · Launch blockers | C7: Keep LifeShare and on-hold module routes unreachable | D7: Task | E7: Web + Mobile | F7: — | G7: — | H7: 2 | I7: P0 | J7: 0 · Foundations | K7: 2 | L7: On-hold modules (LifeShare, incident mocks) must not be reachable in production builds. Gate them behind VITE_ENABLE_ON_HOLD_MODULES (default off). | M7: • Production build has no route to on-hold modules • Flag documented in env example | R7: To do | U7: SKB-006
A8: SK-007 | B8: E1 · Design system foundations | C8: Apply design-token foundations and adopt one palette (D1) and font (D2) | D8: Task | E8: Web + Mobile | F8: IconSystem, MotionSystem | G8: 8 · Design system & flow map | H8: 3 | I8: P0 | J8: 0 · Foundations | K8: 5 | L8: Merge the design-system foundations patch (DESIGN.md, token JSON, generator, contrast test). Then, after product sign-off, point tokens.ts and workflows.css at the generated values and use Plus Jakarta Sans everywhere. | M8: • npm run tokens:check passes in CI • Runtime theme uses generated tokens • Plus Jakarta Sans loaded for UI, IBM Plex Mono for values • Contrast test green | Q8: Decisions D1 (palette), D2 (font), D3 (dark mode) need an owner. | R8: To do
A9: SK-008 | B9: E1 · Design system foundations | C9: Set up Storybook with accessibility and visual-regression checks | D9: Task | E9: Web | F9: — | G9: — | H9: 3 | I9: P0 | J9: 0 · Foundations | K9: 5 | L9: Every core component needs stories for every state. Add Storybook (react-native-web), the a11y addon and a visual-regression step in CI. | M9: • Storybook runs locally and in CI • axe checks fail the build on violations • Visual snapshots stored per story | R9: To do
A10: SK-009 | B10: E1 · Design system foundations | C10: Lint rule that blocks new hard-coded colours | D10: Task | E10: Web + Mobile | F10: — | G10: — | H10: 3 | I10: P1 | J10: 2 · Launch month | K10: 2 | L10: About 3,090 raw hex values exist in 171 files. Add a lint rule that fails on new hex values outside the design-system folder; migrate old ones when a screen is touched. | M10: • New hex value fails lint • Existing files allow-listed with a count that can only go down | N10: SK-007 | O10: Apply design-token foundations and adopt one palette (D1) and font (D2) | R10: To do
A11: SK-010 | B11: E1 · Design system foundations | C11: Buttons and form inputs | D11: Story | E11: Web + Mobile | F11: Feedback, SignIn, OtpVerify, CreateAccount | G11: 8 · Design system & flow map, 1 · Launch & onboarding | H11: 3 | I11: P0 | J11: 0 · Foundations | K11: 5 | L11: Button (primary, secondary, ghost, danger) and inputs: text, select, 6-digit code, +91 phone. These are used on nearly every screen. | M11: • All variants and states have stories (default, hover, focus, busy, disabled, invalid) • 50 px inputs/buttons, 54 px primary CTA, 44 px hit areas • Error message linked with aria-describedby | N11: SK-008 | O11: Set up Storybook with accessibility and visual-regression checks | R11: To do
A12: SK-011 | B12: E1 · Design system foundations | C12: Checkbox, switch, radio and chips | D12: Story | E12: Web + Mobile | F12: OnboardingConsent, NotificationSettings, Permissions | G12: 1 · Launch & onboarding, 2 · Student app (mobile) | H12: 3 | I12: P0 | J12: 0 · Foundations | K12: 3 | L12: Selection controls used in consent, settings and filters. | M12: • off/on/disabled/focus stories • Real input elements with labels • Consent checkboxes never pre-ticked | N12: SK-008 | O12: Set up Storybook with accessibility and visual-regression checks | R12: To do
A13: SK-012 | B13: E1 · Design system foundations | C13: Cards, list rows, section headers, notes and banners | D13: Story | E13: Web + Mobile | F13: Feedback, MoreHub, YourCare | G13: 8 · Design system & flow map, 2 · Student app (mobile) | H13: 3 | I13: P0 | J13: 0 · Foundations | K13: 5 | L13: Layout building blocks: card, list row (with chevron/action), eyebrow section header, note/banner in info, positive, attention and danger. | M13: • Stories for default, selected, with action • Note tones use semantic tokens (out-of-range = attention/amber, never red) | N13: SK-008 | O13: Set up Storybook with accessibility and visual-regression checks | R13: To do
A14: SK-013 | B14: E1 · Design system foundations | C14: Toasts and inline validation | D14: Story | E14: Web + Mobile | F14: Feedback | G14: 8 · Design system & flow map | H14: 3 | I14: P0 | J14: 0 · Foundations | K14: 3 | L14: Neutral, success and error toasts (wrap on phone) and inline field validation from the Feedback board. | M14: • role="status" for toasts • Toasts never carry health values | N14: SK-010 | O14: Buttons and form inputs | R14: To do
A15: SK-014 | B15: E1 · Design system foundations | C15: Bottom sheet, drawer, dialog and confirm dialogs | D15: Story | E15: Web + Mobile | F15: Sheets, NavSheets, ConfirmDialogs | G15: 8 · Design system & flow map | H15: 3 | I15: P0 | J15: 0 · Foundations | K15: 5 | L15: Phone bottom sheets, web drawers and dialogs, plus the confirm dialogs for log out, cancel booking and revoke access. | M15: • aria-modal + focus trap + Esc closes • open, busy, done states • Cancel as easy as confirm | N15: SK-010 | O15: Buttons and form inputs | R15: To do
A16: SK-015 | B16: E1 · Design system foundations | C16: Empty, loading, error and offline states | D16: Story | E16: Web + Mobile | F16: StateScreens | G16: 8 · Design system & flow map | H16: 3 | I16: P0 | J16: 0 · Foundations | K16: 5 | L16: Shared full-screen and inline states for every role: skeleton loading, empty with one next step, error with retry and reference code, offline banner. | M16: • One component per state with role-specific copy props • Error copy says whose side the problem is on | N16: SK-012 | O16: Cards, list rows, section headers, notes and banners | R16: To do
A17: SK-016 | B17: E1 · Design system foundations | C17: Result moments (success, failure, pending) | D17: Story | E17: Web + Mobile | F17: StatusMoments | G17: 8 · Design system & flow map | H17: 3 | I17: P1 | J17: 2 · Launch month | K17: 3 | L17: Full-screen outcome for bookings and payments. | M17: • Success animation only for commerce and bookings • Reduced motion respected • Failure shows what to do next | N17: SK-015 | O17: Empty, loading, error and offline states | Q17: Never celebrate anything about the body. | R17: To do | U17: SKB-027
A18: SK-017 | B18: E1 · Design system foundations | C18: Navigation: phone tab bar, web header, footer and role sidebars | D18: Story | E18: Web + Mobile | F18: NavSheets, Landing, WebHome, ClinicianConsole, VendorConsole, CampusAdminConsole, SuperAdminConsole | G18: 8 · Design system & flow map, 3a · Student web — public site, 3b · Student web — signed in, 5 · Doctor, 6 · Partner — pharmacy, lab, clinic, 4 · Campus / hostel admin, 7 · Super admin | H18: 3 | I18: P0 | J18: 0 · Foundations | K18: 8 | L18: Option B tab bar on phone (Discover, Shop, Your Care, Records, More), the public web header and footer, the signed-in student web menu, and one sidebar per console role with the current page highlighted. | M18: • Same student web menu on every signed-in page • Console sidebars for doctor, partner, campus, super admin • Current page marked with aria-current | N18: SK-010 | O18: Buttons and form inputs | R18: To do | U18: SKB-017, SKB-037
A19: SK-018 | B19: E1 · Design system foundations | C19: Icon set, illustrations and motion system | D19: Story | E19: Web + Mobile | F19: IconSystem, IllustrationLibrary, MotionSystem | G19: 8 · Design system & flow map | H19: 3 | I19: P1 | J19: 2 · Launch month | K19: 5 | L19: Flat and 3D icons, the illustration library and motion tokens (160/320/420 ms) as reusable assets. | M19: • Icons exported as components with aria-hidden by default • All motion stops under prefers-reduced-motion | N19: SK-007 | O19: Apply design-token foundations and adopt one palette (D1) and font (D2) | R19: To do
A20: SK-019 | B20: E1 · Design system foundations | C20: Console data table | D20: Story | E20: Web | F20: CampusRoster, AdminAccounts, AuditExplorer, LabQueue | G20: 4 · Campus / hostel admin, 7 · Super admin, 6 · Partner — pharmacy, lab, clinic | H20: 3 | I20: P0 | J20: 0 · Foundations | K20: 5 | L20: Shared table for all consoles: sorting, filters, row actions, pagination, and loading/empty/error rows. | M20: • Keyboard navigable • Stories for data, loading, empty, error • No PHI in exported CSV unless the role allows it | N20: SK-015 | O20: Empty, loading, error and offline states | R20: To do | U20: SKB-038
A21: SK-020 | B21: E1 · Design system foundations | C21: Ayush chat component (web widget and phone sheet) | D21: Story | E21: Web + Mobile | F21: AyushWidget, AyushSheet | G21: 8 · Design system & flow map | H21: 1 | I21: P1 | J21: 2 · Launch month | K21: 5 | L21: One chat component in two shells: the web widget and the phone bottom sheet with context chips. | M21: • Crisis words show the crisis card instead of an AI answer • Dose or diagnosis questions route to a doctor • Web widget docks to the bottom-right of the viewport, never over page content | N21: SK-014 | O21: Bottom sheet, drawer, dialog and confirm dialogs | Q21: Ayush never diagnoses or prescribes. | R21: To do | U21: SKB-028
A22: SK-021 | B22: E1 · Design system foundations | C22: Languages: English, Telugu and Hindi | D22: Story | E22: Web + Mobile | F22: CrisisSupport, SosBeacon, EmergencyCard, SignIn, WebSignIn, OnboardingConsent | G22: 2 · Student app (mobile), 1 · Launch & onboarding, 3b · Student web — signed in | H22: 1 | I22: P0 | J22: 0 · Foundations | K22: 5 | L22: i18n set-up and translations, starting with safety, sign-in and consent screens. Names, phone numbers, "WhatsApp", "ABHA" and helpline names stay in English. | M22: • Language switch persists • Noto Sans Telugu / Devanagari loaded • Native-speaker review on crisis copy before launch • No truncation in any language | R22: To do | U22: SKB-041
A23: SK-022 | B23: E1 · Design system foundations | C23: Route map and deep links from the flow map | D23: Task | E23: Web + Mobile | F23: FlowMap | G23: 8 · Design system & flow map | H23: 3 | I23: P1 | J23: 2 · Launch month | K23: 3 | L23: Use the canvas flow map (148 nodes) as the source for the route table, so every screen has a route and every link on the canvas has a destination. | M23: • Route table documented • Deep links for pass, order tracking, guardian approval, report • No dead links between built screens | R23: To do
A24: SK-023 | B24: E2 · Launch, sign-in & onboarding | C24: Splash that changes with the time of day | D24: Story | E24: Mobile | F24: Main, SplashPulse, SplashVault | G24: 1 · Launch & onboarding | H24: 3 | I24: P1 | J24: 2 · Launch month | K24: 3 | L24: One bright splash with three variants: morning (doctor), afternoon (heartbeat), evening (care circle), chosen by local hour. | M24: • 5–12 doctor, 12–18 heartbeat, else care circle • Under 2 s; no blocking animation • Reduced motion shows a still frame | N24: SK-018 | O24: Icon set, illustrations and motion system | R24: To do
A25: SK-024 | B25: E2 · Launch, sign-in & onboarding | C25: Onboarding carousel | D25: Story | E25: Mobile | F25: Onboarding1, Onboarding2, Onboarding3 | G25: 1 · Launch & onboarding | H25: 3 | I25: P1 | J25: 2 · Launch month | K25: 3 | L25: Three intro slides: campus care, health vault, Ayush. Skippable. | M25: • Swipe and buttons both work • Skip goes to sign in • Screen reader announces slide n of 3 | N25: SK-010 | O25: Buttons and form inputs | R25: To do
A26: SK-025 | B26: E2 · Launch, sign-in & onboarding | C26: Sign in with phone and OTP | D26: Story | E26: Mobile | F26: SignIn, OtpVerify | G26: 1 · Launch & onboarding | H26: 2 | I26: P0 | J26: 1 · Launch | K26: 5 | L26: Phone number sign-in with a 6-digit code, resend timer and lockout. | M26: • +91 10-digit validation • 5 wrong codes → 10-minute lock with message • Resend after 30 s • Crisis/SOS link visible before sign-in | N26: SK-003, SK-010 | O26: Turn demo mode off by default (no demo admin, no fixed OTP); Buttons and form inputs | P26: POST /auth/otp/send, /auth/otp/verify | R26: To do
A27: SK-026 | B27: E2 · Launch, sign-in & onboarding | C27: Create account, campus, care profile and permissions | D27: Story | E27: Mobile | F27: CreateAccount, CampusVerify, ProfileSetup, Permissions, AccountReady | G27: 1 · Launch & onboarding | H27: 2 | I27: P0 | J27: 1 · Launch | K27: 8 | L27: The sign-up steps after the first OTP: name and email, campus and hostel, care basics, device permissions, then "Workspace ready". | M27: • Progress shows step n of 6 • Each step saves; back keeps entries • Permissions explained before the OS prompt; all optional • Blood group defaults to "Not set" | N27: SK-025 | O27: Sign in with phone and OTP | P27: POST /students, /students/{id}/campus | R27: To do | U27: SKB-012
A28: SK-027 | B28: E2 · Launch, sign-in & onboarding | C28: Data-protection consent (DPDP) | D28: Story | E28: Mobile | F28: OnboardingConsent | G28: 1 · Launch & onboarding | H28: 1 | I28: P0 | J28: 1 · Launch | K28: 5 | L28: Plain-language consent: what we keep, never do, what you can do, how long. Three required ticks, three optional switches off by default. | M28: • Continue locked until the 3 required items are ticked • Consent version (v3.1) + timestamp stored • English, Telugu, Hindi • Link to full privacy notice and grievance officer | N28: SK-026, SK-021 | O28: Create account, campus, care profile and permissions; Languages: English, Telugu and Hindi | P28: POST /consents (version, items, time) | Q28: No pre-ticked consent. Withdrawing is as easy as agreeing. | R28: To do | U28: SKB-012
A29: SK-028 | B29: E2 · Launch, sign-in & onboarding | C29: Link ABHA | D29: Story | E29: Mobile | F29: AbhaLink | G29: 1 · Launch & onboarding | H29: 2 | I29: P1 | J29: 2 · Launch month | K29: 5 | L29: Link or create an ABHA number so records can be pulled from ABDM. | M29: • Create or link paths • Failure shows reason and a skip option • Only the ABHA number is shown masked | N29: SK-026 | O29: Create account, campus, care profile and permissions | P29: ABDM gateway (ABHA create/link) | R29: To do
A30: SK-029 | B30: E2 · Launch, sign-in & onboarding | C30: Verify it’s you — four identity checks | D30: Story | E30: Mobile | F30: VerifyIdentity | G30: 1 · Launch & onboarding | H30: 1 | I30: P0 | J30: 1 · Launch | K30: 8 | L30: Selfie, email code, college ID (roll number + card photo) and government ID (DigiLocker by default). All four needed before booking, ordering or sharing. | M30: • States per check: to do, busy, done, failed, in review • Failures: photo unclear, college rejects, name mismatch, code locked — each with a fix • Only last 4 Aadhaar digits stored | N30: SK-026 | O30: Create account, campus, care profile and permissions | P30: Identity verification service + college confirmation | R30: To do | U30: SKB-007, SKB-008
A31: SK-030 | B31: E2 · Launch, sign-in & onboarding | C31: Verification gate on services | D31: Story | E31: Mobile | F31: VerifyGate | G31: 1 · Launch & onboarding | H31: 1 | I31: P0 | J31: 1 · Launch | K31: 3 | L31: When an unverified student taps book, order or share, show the gate with progress and a way to finish. | M31: • Crisis support, SOS, emergency card and help never gated • "Not now" returns to where the student was | N31: SK-029 | O31: Verify it’s you — four identity checks | R31: To do | U31: SKB-009
A32: SK-031 | B32: E2 · Launch, sign-in & onboarding | C32: Under-18: ask a guardian and guardian approval | D32: Story | E32: Mobile + Web | F32: GuardianConsent, GuardianApprove | G32: 1 · Launch & onboarding | H32: 1 | I32: P0 | J32: 1 · Launch | K32: 8 | L32: Students under 18 send an SMS link to a parent or guardian, who approves with an OTP. Limited account until approved; consent ends on the 18th birthday. | M32: • Guardian page works without an app or account • Approve / decline / withdraw (reply STOP) • Student sees status and can still reach crisis support and SOS | N32: SK-027 | O32: Data-protection consent (DPDP) | P32: Guardian consent + SMS | Q32: DECISION NEEDED: AGENTS.md says 18+ only. Guardian never sees records, counselling or sexual-health details. | R32: To do | U32: SKB-011
A33: SK-032 | B33: E2 · Launch, sign-in & onboarding | C33: Sign out and logged-out page | D33: Story | E33: Mobile | F33: SignOut, LoggedOut | G33: 1 · Launch & onboarding | H33: 3 | I33: P1 | J33: 2 · Launch month | K33: 2 | L33: Confirm popup before signing out, then a logged-out page with optional feedback. | M33: • Confirm dialog busy → done • Tokens cleared; offline emergency card kept unless the student chooses otherwise | N33: SK-014 | O33: Bottom sheet, drawer, dialog and confirm dialogs | R33: To do | U33: SKB-013
A34: SK-033 | B34: E2 · Launch, sign-in & onboarding | C34: Lost phone and moving to a new phone | D34: Story | E34: Mobile | F34: LostPhone, NewDevice | G34: 1 · Launch & onboarding | H34: 1 | I34: P0 | J34: 1 · Launch | K34: 8 | L34: From a friend’s phone: cancel the check-in pass, sign the lost device out, review the last 24 h of check-ins. New phone: email code + selfie to move the account. | M34: • Pass cancelled immediately • Offline card wiped on the lost device’s next connection • New-device move needs email code + selfie match | N34: SK-057 | O34: Student check-in pass and handover receipt | P34: Device sessions revoke, pass revoke | R34: To do | U34: SKB-014
A35: SK-034 | B35: E3 · Student app — home, search & care | C35: Home / Discover | D35: Story | E35: Mobile | F35: HomeDiscover | G35: 2 · Student app (mobile) | H35: 2 | I35: P0 | J35: 1 · Launch | K35: 5 | L35: The first screen after sign-in: search, quick actions, campus services and the Ayush entry. | M35: • Loading, first-time and offline states • Nothing on Home is chosen from health records • Ask Ayush opens the phone sheet | N35: SK-017, SK-020 | O35: Navigation: phone tab bar, web header, footer and role sidebars; Ayush chat component (web widget and phone sheet) | R35: To do
A36: SK-035 | B36: E3 · Student app — home, search & care | C36: Search: entry, suggestions, loading, results, no results | D36: Story | E36: Mobile | F36: SearchEntry, SearchTyping, SearchLoading, SearchResults, NoResults | G36: 2 · Student app (mobile) | H36: 2 | I36: P0 | J36: 1 · Launch | K36: 8 | L36: One search across lab tests, doctors, medicines and products, with tabs. | M36: • Suggestions after 2 characters, debounced • Skeletons while loading • No results suggests a next step • Recent searches can be cleared | N36: SK-034 | O36: Home / Discover | P36: GET /search?q=&type= | R36: To do
A37: SK-036 | B37: E3 · Student app — home, search & care | C37: Lab test results and booking | D37: Story | E37: Mobile | F37: LabResults, LabPackages, ResultLabBooked | G37: 2 · Student app (mobile) | H37: 2 | I37: P0 | J37: 1 · Launch | K37: 8 | L37: Browse and book lab tests and packages with dorm pickup slots; price shown before booking. | M37: • Slots left per day shown • NABL badge from data, not hard-coded • Booking confirmation moment | N37: SK-035, SK-030 | O37: Search: entry, suggestions, loading, results, no results; Verification gate on services | P37: Lab catalogue, slots, bookings | R37: To do
A38: SK-037 | B38: E3 · Student app — home, search & care | C38: Doctor results and appointments | D38: Story | E38: Mobile | F38: DoctorResults, Appointments | G38: 2 · Student app (mobile) | H38: 2 | I38: P0 | J38: 1 · Launch | K38: 5 | L38: Find a doctor (NMC-registered), see price and next slot, book, and manage upcoming appointments. | M38: • Price before booking • Reschedule and cancel with confirm dialog • Empty and offline states | N38: SK-035, SK-030 | O38: Search: entry, suggestions, loading, results, no results; Verification gate on services | P38: Clinician directory, slots, appointments | R38: To do
A39: SK-038 | B39: E3 · Student app — home, search & care | C39: Teleconsult call | D39: Story | E39: Mobile | F39: Teleconsult | G39: 2 · Student app (mobile) | H39: 1 | I39: P0 | J39: 1 · Launch | K39: 8 | L39: Video consult with a doctor: pre-call check, in-call controls, end call. | M39: • Camera/mic permission explained • Reconnect on network drop • Ends into the visit summary | N39: SK-037 | O39: Doctor results and appointments | P39: Video provider + consult session | R39: To do
A40: SK-039 | B40: E3 · Student app — home, search & care | C40: Visit summary and e-prescription | D40: Story | E40: Mobile + Web | F40: ConsultSummary, WebConsultSummary | G40: 2 · Student app (mobile), 3b · Student web — signed in | H40: 1 | I40: P0 | J40: 1 · Launch | K40: 8 | L40: After a consult: plain-language notes, red flags, signed e-prescription, order medicines or take the Rx anywhere, follow-up, rating. | M40: • Rx carries doctor NMC number and signature • Allergy check shown • Order here or download — student’s choice | N40: SK-038 | O40: Teleconsult call | P40: Encounter summary + Rx | R40: To do | U40: SKB-025
A41: SK-040 | B41: E3 · Student app — home, search & care | C41: Your Care overview | D41: Story | E41: Mobile | F41: YourCare | G41: 2 · Student app (mobile) | H41: 2 | I41: P0 | J41: 1 · Launch | K41: 5 | L41: This week summary, items that need the student, and semester progress. | M41: • First-time and offline states • Every number comes from real data • Ask Ayush opens with "care" context | N41: SK-034 | O41: Home / Discover | R41: To do | U41: SKB-039
A42: SK-041 | B42: E3 · Student app — home, search & care | C42: Medicines and refill requests | D42: Story | E42: Mobile | F42: Medications, RefillRequest | G42: 2 · Student app (mobile) | H42: 1 | I42: P1 | J42: 2 · Launch month | K42: 5 | L42: Medicine list with dose ticks and refill requests to a pharmacy or doctor. | M42: • Ticking a dose records it; nothing is scored • Refill shows price and pickup before confirming | N42: SK-040 | O42: Your Care overview | P42: Medication list, refill requests | R42: To do
A43: SK-042 | B43: E3 · Student app — home, search & care | C43: Preventive care | D43: Story | E43: Mobile | F43: PreventiveCare | G43: 2 · Student app (mobile) | H43: 2 | I43: P2 | J43: 3 · Later | K43: 3 | L43: Vaccinations and routine checks due, with booking links. | M43: • Due dates from records • No alarming language | N43: SK-040 | O43: Your Care overview | R43: To do
A44: SK-043 | B44: E3 · Student app — home, search & care | C44: Devices and typed readings | D44: Story | E44: Mobile | F44: Devices | G44: 2 · Student app (mobile) | H44: 1 | I44: P1 | J44: 2 · Launch month | K44: 5 | L44: Pair real devices or type a reading. Each reading shows its source. | M44: • "Typed by you" or device badge on every reading • No camera vitals | N44: SK-002 | O44: Remove camera vitals and the fake readings they create | P44: Readings API with source field | R44: To do
A45: SK-044 | B45: E3 · Student app — home, search & care | C45: Movement | D45: Story | E45: Mobile | F45: Movement | G45: 2 · Student app (mobile) | H45: 3 | I45: P2 | J45: 3 · Later | K45: 3 | L45: Sessions this week from guides the student chose. | M45: • No body scores or rankings • Empty state with one next step | N45: SK-040 | O45: Your Care overview | R45: To do
A46: SK-045 | B46: E3 · Student app — home, search & care | C46: Vital trends | D46: Story | E46: Mobile | F46: VitalTrends | G46: 2 · Student app (mobile) | H46: 1 | I46: P1 | J46: 2 · Launch month | K46: 5 | L46: Charts of readings over time with the lab or device reference range. | M46: • Out of range shown in amber, never red • Source badge per point • Clinical values in mono font | N46: SK-043 | O46: Devices and typed readings | Q46: Tier 1: clinical review of design before build. | R46: To do
A47: SK-046 | B47: E3 · Student app — home, search & care | C47: Health vault (records) | D47: Story | E47: Mobile | F47: RecordsVault | G47: 2 · Student app (mobile) | H47: 1 | I47: P0 | J47: 1 · Launch | K47: 8 | L47: All documents and reports, filterable, with upload and share. | M47: • Upload photo/PDF • Every share shows who, what and until when, and can be revoked • Offline: cached list read-only | N47: SK-040 | O47: Your Care overview | P47: Documents API, ABDM pull | R47: To do
A48: SK-047 | B48: E3 · Student app — home, search & care | C48: My lab tests and report insights | D48: Story | E48: Mobile | F48: MyReports, ReportInsights | G48: 2 · Student app (mobile) | H48: 1 | I48: P0 | J48: 1 · Launch | K48: 8 | L48: Track lab bookings through collection to report, then a plain-language explanation of results. | M48: • Status timeline per test • Out-of-range values amber with "talk to a doctor" link • No diagnosis language | N48: SK-036 | O48: Lab test results and booking | P48: Lab orders + results | R48: To do
A49: SK-048 | B49: E3 · Student app — home, search & care | C49: Ayush chat (full screen) | D49: Story | E49: Mobile | F49: AyushChat | G49: 2 · Student app (mobile) | H49: 1 | I49: P1 | J49: 2 · Launch month | K49: 5 | L49: Full-screen Ayush for longer conversations; same rules as the sheet. | M49: • History can be cleared • Crisis words → crisis card • Clear label that Ayush is an assistant, not a doctor | N49: SK-020 | O49: Ayush chat component (web widget and phone sheet) | R49: To do
A50: SK-049 | B50: E3 · Student app — home, search & care | C50: Notifications inbox | D50: Story | E50: Mobile | F50: Notifications | G50: 2 · Student app (mobile) | H50: 3 | I50: P1 | J50: 2 · Launch month | K50: 3 | L50: In-app list of updates with read/unread. | M50: • Group by day • Tap opens the related screen • No health values in previews | N50: SK-017 | O50: Navigation: phone tab bar, web header, footer and role sidebars | R50: To do
A51: SK-050 | B51: E4 · Student safety & privacy | C51: Offline emergency card and emergency contacts | D51: Story | E51: Mobile | F51: EmergencyCard, IceContacts | G51: 2 · Student app (mobile) | H51: 1 | I51: P0 | J51: 1 · Launch | K51: 8 | L51: An emergency card that works offline and from the lock screen, plus the contacts it lists. | M51: • Blood group defaults to "Not set"; explicit "No known allergies" • +91 10-digit validation • Nothing on the card is sent anywhere | N51: SK-026 | O51: Create account, campus, care profile and permissions | R51: To do | U51: SKB-029
A52: SK-051 | B52: E4 · Student safety & privacy | C52: Crisis support | D52: Story | E52: Mobile | F52: CrisisSupport | G52: 2 · Student app (mobile) | H52: 1 | I52: P0 | J52: 1 · Launch | K52: 5 | L52: Always-reachable crisis screen: campus SOS, helplines, counsellor booking. | M52: • Reachable without sign-in, verification or network • Campus never sees that it was opened • Telugu and Hindi reviewed | N52: SK-021 | O52: Languages: English, Telugu and Hindi | Q52: Never behind a login, gate, paywall or loading state. | R52: To do
A53: SK-052 | B53: E4 · Student safety & privacy | C53: SOS beacon and after-SOS | D53: Story | E53: Mobile | F53: SosBeacon, SosDebrief | G53: 2 · Student app (mobile) | H53: 1 | I53: P0 | J53: 1 · Launch | K53: 8 | L53: Trigger SOS, share location with campus responders, then a debrief showing who was told. | M53: • Hold-to-confirm with cancel window • Works on poor network (SMS fallback) • Debrief offers a counsellor call and a private note | N53: SK-050 | O53: Offline emergency card and emergency contacts | P53: SOS event + responder notify | R53: To do | U53: SKB-026
A54: SK-053 | B54: E4 · Student safety & privacy | C54: Consent inbox | D54: Story | E54: Mobile | F54: ConsentInbox | G54: 2 · Student app (mobile) | H54: 1 | I54: P0 | J54: 1 · Launch | K54: 5 | L54: Requests from doctors, labs or campus to see records; approve, limit or decline. | M54: • Each request shows who, what, until when • Revoke any time • Declined requests leave no trace for the requester beyond "declined" | N54: SK-046 | O54: Health vault (records) | P54: ABDM consent manager | R54: To do
A55: SK-054 | B55: E4 · Student safety & privacy | C55: Care Circle | D55: Story | E55: Mobile | F55: FamilyCircle | G55: 2 · Student app (mobile) | H55: 1 | I55: P1 | J55: 2 · Launch month | K55: 5 | L55: Share selected records with family members, each with a separate private record. | M55: • Invite by phone • Per-person share scopes • Remove member instantly | N55: SK-053 | O55: Consent inbox | R55: To do
A56: SK-055 | B56: E4 · Student safety & privacy | C56: Download my data | D56: Story | E56: Mobile | F56: DataExport | G56: 2 · Student app (mobile) | H56: 2 | I56: P1 | J56: 2 · Launch month | K56: 3 | L56: Export all records and account data. | M56: • Choose scope and format • Link expires; sent only to the verified email | N56: SK-046 | O56: Health vault (records) | P56: Export job | R56: To do
A57: SK-056 | B57: E4 · Student safety & privacy | C57: Hostel room visit | D57: Story | E57: Mobile | F57: HostelVisit | G57: 2 · Student app (mobile) | H57: 2 | I57: P2 | J57: 3 · Later | K57: 3 | L57: Request a campus nurse or doctor visit to the hostel room. | M57: • Time window and price shown • Status updates | N57: SK-030 | O57: Verification gate on services | P57: Visit requests | R57: To do
A58: SK-057 | B58: E4 · Student safety & privacy | C58: Student check-in pass and handover receipt | D58: Story | E58: Mobile | F58: MyPass, CheckinReceipt | G58: 2 · Student app (mobile) | H58: 1 | I58: P0 | J58: 1 · Launch | K58: 8 | L58: Rotating QR and 6-digit code for pharmacy, lab and clinic; history with "This wasn’t me"; receipt with bag photo after handover. | M58: • QR and code rotate every 30 s, work offline • Screenshots fail (signed, time-bound) • Receipt links to report or return | N58: SK-029 | O58: Verify it’s you — four identity checks | P58: Pass signing service | R58: To do | U58: SKB-018, SKB-023
A59: SK-058 | B59: E4 · Student safety & privacy | C59: Leaving campus | D59: Story | E59: Mobile | F59: LeaveCampus | G59: 2 · Student app (mobile) | H59: 2 | I59: P1 | J59: 2 · Launch month | K59: 3 | L59: Move to a personal account when leaving campus. | M59: • Personal email required • Effective date by reason • Undo available | N59: SK-069 | O59: Account details | R59: To do | U59: SKB-015
A60: SK-059 | B60: E4 · Student safety & privacy | C60: Delete my account | D60: Story | E60: Mobile | F60: DeleteAccount | G60: 2 · Student app (mobile) | H60: 1 | I60: P0 | J60: 1 · Launch | K60: 5 | L60: Type DELETE and confirm with a phone code; 7 days to cancel; list what must legally be kept. | M60: • 7-day cancel window • Erasure completed within 30 days after the window • "Having a hard time?" shows support | N60: SK-069 | O60: Account details | P60: DPDP erasure request | R60: To do | U60: SKB-016
A61: SK-060 | B61: E4 · Student safety & privacy | C61: Privacy notice, terms and grievance officer | D61: Story | E61: Mobile | F61: Legal | G61: 2 · Student app (mobile) | H61: 1 | I61: P0 | J61: 1 · Launch | K61: 3 | L61: Legal pages and grievance form; every legal link in the app lands here. | M61: • Grievance form returns a reference • 48 h acknowledgement, 30-day resolution stated | Q61: Real grievance officer details and legal review needed before launch. | R61: To do | U61: SKB-031
A62: SK-061 | B62: E4 · Student safety & privacy | C62: Notification settings | D62: Story | E62: Mobile | F62: NotificationSettings | G62: 2 · Student app (mobile) | H62: 2 | I62: P1 | J62: 2 · Launch month | K62: 3 | L62: Channels, categories, quiet hours and lock-screen privacy. | M62: • Lock-screen privacy on by default • Safety alerts always on • Partner offers off by default | N62: SK-011 | O62: Checkbox, switch, radio and chips | R62: To do | U62: SKB-032
A63: SK-062 | B63: E5 · Student app — shop & orders | C63: Shop home, product list and product detail | D63: Story | E63: Mobile | F63: ShopHome, ProductList, ProductDetail | G63: 2 · Student app (mobile) | H63: 2 | I63: P0 | J63: 1 · Launch | K63: 8 | L63: Wellness shop with categories, dorm staples, product grid and detail. | M63: • Prices and delivery shown before adding • "Nothing here is chosen from your health records" shown • Stock from the partner | N63: SK-017 | O63: Navigation: phone tab bar, web header, footer and role sidebars | P63: Catalogue + stock | Q63: Rule L: no health data on commerce surfaces, no sponsored placement. | R63: To do
A64: SK-063 | B64: E5 · Student app — shop & orders | C64: Cart, checkout and payment | D64: Story | E64: Mobile | F64: Cart, Checkout, Payment, PaymentResult, OrderSuccess | G64: 2 · Student app (mobile) | H64: 2 | I64: P0 | J64: 1 · Launch | K64: 8 | L64: Cart, delivery address (hostel block), payment (UPI, card) and result. | M64: • Total incl. delivery shown before paying • Payment failed / pending states • Order placed moment (commerce only) | N64: SK-062, SK-016 | O64: Shop home, product list and product detail; Result moments (success, failure, pending) | P64: Orders + payment gateway | R64: To do
A65: SK-064 | B65: E5 · Student app — shop & orders | C65: Order tracking and order history | D65: Story | E65: Mobile | F65: OrderTracking, OrderHistory | G65: 2 · Student app (mobile) | H65: 2 | I65: P0 | J65: 1 · Launch | K65: 5 | L65: Live order status and past orders with reorder. | M65: • Timeline with times • Handover with pass check shown • Offline shows last known status | N65: SK-063 | O65: Cart, checkout and payment | P65: Order status | R65: To do
A66: SK-065 | B66: E5 · Student app — shop & orders | C66: Prescription upload | D66: Story | E66: Mobile | F66: PrescriptionUpload | G66: 2 · Student app (mobile) | H66: 1 | I66: P0 | J66: 1 · Launch | K66: 5 | L66: Upload a prescription for Rx medicines; pharmacist reviews before dispatch. | M66: • Photo or PDF • Status: in review / approved / needs a clearer copy • Rx items blocked until approved | N66: SK-063 | O66: Cart, checkout and payment | P66: Rx upload + pharmacist review | R66: To do
A67: SK-066 | B67: E5 · Student app — shop & orders | C67: Returns and refunds | D67: Story | E67: Mobile | F67: ReturnRequest, ResultRefund | G67: 2 · Student app (mobile) | H67: 2 | I67: P1 | J67: 2 · Launch month | K67: 5 | L67: Return an unopened item within 7 days and track the refund. | M67: • Reason, photo, pickup from block • Refund started moment | N67: SK-064 | O67: Order tracking and order history | P67: Returns + refunds | R67: To do
A68: SK-067 | B68: E5 · Student app — shop & orders | C68: Camp booking result | D68: Story | E68: Mobile | F68: ResultCampBooked | G68: 2 · Student app (mobile) | H68: 2 | I68: P1 | J68: 2 · Launch month | K68: 2 | L68: Confirmation after booking a health camp slot. | M68: • Slot, place, what to bring • Add to calendar | N68: SK-016 | O68: Result moments (success, failure, pending) | R68: To do
A69: SK-068 | B69: E6 · Student app — account | C69: More hub, profile and digital health ID | D69: Story | E69: Mobile | F69: MoreHub, StudentProfile, DigitalId | G69: 2 · Student app (mobile) | H69: 2 | I69: P0 | J69: 1 · Launch | K69: 5 | L69: Account hub, profile card and the digital health ID with ABHA. | M69: • Verified badge + 4 check chips • ABHA number masked • Log out confirm on every account screen | N69: SK-017 | O69: Navigation: phone tab bar, web header, footer and role sidebars | R69: To do | U69: SKB-010
A70: SK-069 | B70: E6 · Student app — account | C70: Account details | D70: Story | E70: Mobile | F70: AccountDetails | G70: 2 · Student app (mobile) | H70: 2 | I70: P0 | J70: 1 · Launch | K70: 3 | L70: Name, phone, email, campus, block; change with verification. | M70: • Phone/email change needs a code • Verified status shown | N70: SK-068 | O70: More hub, profile and digital health ID | R70: To do
A71: SK-070 | B71: E6 · Student app — account | C71: Plan and billing | D71: Story | E71: Mobile | F71: PlanBilling | G71: 2 · Student app (mobile) | H71: 2 | I71: P1 | J71: 2 · Launch month | K71: 3 | L71: Current plan, invoices, upgrade/cancel. | M71: • Price from the single source • Cancel as easy as upgrade | N71: SK-005 | O71: One source of truth for the Student Plus price | R71: To do
A72: SK-071 | B72: E6 · Student app — account | C72: Cover and claims | D72: Story | E72: Mobile | F72: ClaimsHub | G72: 2 · Student app (mobile) | H72: 2 | I72: P2 | J72: 3 · Later | K72: 5 | L72: Insurance cover and claim status. | M72: • Claim timeline • Documents attached from the vault with consent | N72: SK-046 | O72: Health vault (records) | P72: Claims API | R72: To do
A73: SK-072 | B73: E6 · Student app — account | C73: Help centre and my requests | D73: Story | E73: Mobile | F73: HelpCentre, MyRequests | G73: 2 · Student app (mobile) | H73: 2 | I73: P0 | J73: 1 · Launch | K73: 5 | L73: Help articles, contact support, and a tracked list of every request. | M73: • Every "support will call" promise creates a request with a timeline • Crisis link on help centre | P73: Support tickets | R73: To do | U73: SKB-030
A74: SK-073 | B74: E7 · Public website | C74: Landing — Discover | D74: Story | E74: Web | F74: Landing | G74: 3a · Student web — public site | H74: 3 | I74: P0 | J74: 1 · Launch | K74: 8 | L74: Public home page for students: hero, what you can do, everyday wellness, lab checks, footer and newsletter. | M74: • Responsive 320–1440 px • Videos lazy-load with a still poster and captions off by default • Lighthouse performance ≥ 80 | N74: SK-017 | O74: Navigation: phone tab bar, web header, footer and role sidebars | P74: Public catalogue (read-only) | R74: To do
A75: SK-074 | B75: E7 · Public website | C75: Lab tests landing and category pages | D75: Story | E75: Web | F75: WebLabTests, WebLabList | G75: 3a · Student web — public site | H75: 3 | I75: P0 | J75: 1 · Launch | K75: 8 | L75: Public lab test pages with packages and categories. | M75: • Prices shown; booking requires sign-in • Structured data for tests (SEO) | N75: SK-073 | O75: Landing — Discover | R75: To do
A76: SK-075 | B76: E7 · Public website | C76: Consult a doctor page | D76: Story | E76: Web | F76: WebConsult | G76: 3a · Student web — public site | H76: 3 | I76: P0 | J76: 1 · Launch | K76: 5 | L76: Public page explaining consults, pricing and NMC-registered doctors. | M76: • Price from data • FAQ accordion accessible | N76: SK-073 | O76: Landing — Discover | R76: To do
A77: SK-076 | B77: E7 · Public website | C77: Care programmes and wellness training pages | D77: Story | E77: Web | F77: WebPrograms, WebWellness | G77: 3a · Student web — public site | H77: 3 | I77: P1 | J77: 2 · Launch month | K77: 8 | L77: Programme and wellness pages with weekly schedules. | M77: • Schedules from data • No body scores or before/after claims | N77: SK-073 | O77: Landing — Discover | R77: To do
A78: SK-077 | B78: E7 · Public website | C78: Plans page | D78: Story | E78: Web | F78: WebPlans | G78: 3a · Student web — public site | H78: 3 | I78: P0 | J78: 1 · Launch | K78: 5 | L78: Basic free forever, Premium, Care Circle, Enterprise; comparison table. | M78: • Prices from the single source • "Records never behind a paywall" message | N78: SK-005 | O78: One source of truth for the Student Plus price | R78: To do
A79: SK-078 | B79: E7 · Public website | C79: Landing pages for campuses, clinicians and partners | D79: Story | E79: Web | F79: LandingCampus, LandingClinician, WebPartnerships | G79: 3a · Student web — public site | H79: 3 | I79: P1 | J79: 2 · Launch month | K79: 8 | L79: Three B2B landing pages that lead to the application forms. | M79: • CTA to the right application • Rule L commitments stated for partners | N79: SK-073 | O79: Landing — Discover | R79: To do
A80: SK-079 | B80: E8 · Student web — signed in | C80: Web sign-in, sign-out, logged out and lost phone | D80: Story | E80: Web | F80: WebSignIn, WebSignOut, WebLoggedOut, WebLostPhone | G80: 3b · Student web — signed in, 1 · Launch & onboarding | H80: 2 | I80: P0 | J80: 1 · Launch | K80: 5 | L80: Web versions of sign-in (phone + OTP or QR from the app), logged-out page and lost-phone flow. | M80: • Same rules as phone • Session list visible afterwards | N80: SK-025, SK-033 | O80: Sign in with phone and OTP; Lost phone and moving to a new phone | R80: To do
A81: SK-080 | B81: E8 · Student web — signed in | C81: Web identity verification, gate and guardian consent | D81: Story | E81: Web | F81: WebVerify, WebVerifyGate, WebGuardianConsent, WebGuardianApprove | G81: 3b · Student web — signed in | H81: 1 | I81: P0 | J81: 1 · Launch | K81: 8 | L81: Web layouts for the four identity checks, the service gate and under-18 guardian consent. | M81: • Shares viewmodels with the phone tickets • Gate never blocks crisis, SOS, emergency card, help | N81: SK-029, SK-031 | O81: Verify it’s you — four identity checks; Under-18: ask a guardian and guardian approval | R81: To do
A82: SK-081 | B82: E8 · Student web — signed in | C82: Web home and care dashboard | D82: Story | E82: Web | F82: WebHome, WebDashboard | G82: 3b · Student web — signed in | H82: 2 | I82: P0 | J82: 1 · Launch | K82: 8 | L82: Signed-in home and the care dashboard. | M82: • First-time and offline states • Real data only | N82: SK-040 | O82: Your Care overview | R82: To do
A83: SK-082 | B83: E8 · Student web — signed in | C83: Web health vault | D83: Story | E83: Web | F83: WebVault | G83: 3b · Student web — signed in | H83: 1 | I83: P0 | J83: 1 · Launch | K83: 5 | L83: Records list with upload, filters and sharing. | M83: • Drag-and-drop upload • Share shows who, what, until when; revoke | N83: SK-046 | O83: Health vault (records) | R83: To do
A84: SK-083 | B84: E8 · Student web — signed in | C84: Web lab tests, report insights and report explainer | D84: Story | E84: Web | F84: WebMyLabTests, WebReportInsights, WebReportAssistant | G84: 3b · Student web — signed in | H84: 1 | I84: P0 | J84: 1 · Launch | K84: 8 | L84: Track lab tests, read results and ask Ayush to explain a report. | M84: • Out of range amber, never red • Explainer never diagnoses; links to a doctor | N84: SK-047 | O84: My lab tests and report insights | R84: To do
A85: SK-084 | B85: E8 · Student web — signed in | C85: Web Ayush | D85: Story | E85: Web | F85: WebAyush | G85: 3b · Student web — signed in | H85: 1 | I85: P1 | J85: 2 · Launch month | K85: 3 | L85: Full-page Ayush on web. | M85: • Same rules as the chat component | N85: SK-020 | O85: Ayush chat component (web widget and phone sheet) | R85: To do
A86: SK-085 | B86: E8 · Student web — signed in | C86: Web emergency card and check-in pass | D86: Story | E86: Web | F86: WebEmergencyCard, WebPass | G86: 3b · Student web — signed in | H86: 1 | I86: P0 | J86: 1 · Launch | K86: 5 | L86: Edit the emergency card and show the check-in pass on a computer. | M86: • Same validation as phone • Pass rotates every 30 s | N86: SK-050, SK-057 | O86: Offline emergency card and emergency contacts; Student check-in pass and handover receipt | R86: To do
... A90: SK-089 | B90: E8 · Student web — signed in | C90: Web requests, legal, leaving campus and delete account | D90: Story | E90: Web | F90: WebRequests, WebLegal, WebLeaveCampus, WebDeleteAccount | G90: 3b · Student web — signed in | H90: 1 | I90: P0 | J90: 1 · Launch | K90: 8 | L90: Web versions of my requests, legal pages, leaving campus and delete account. | M90: • Same rules as the phone tickets | N90: SK-072, SK-060, SK-058, SK-059 | O90: Help centre and my requests; Privacy notice, terms and grievance officer; Leaving campus; Delete my account | R90: To do
A91: SK-090 | B91: E9 · Campus admin console | C91: Campus console home and overview | D91: Story | E91: Web | F91: CampusAdminConsole, CampusOverview | G91: 4 · Campus / hostel admin | H91: 3 | I91: P0 | J91: 1 · Launch | K91: 5 | L91: Landing page for campus admins with today’s numbers and shortcuts. | M91: • Only aggregate, anonymous numbers (groups of 20+) • Loading/empty/error states | N91: SK-017, SK-019 | O91: Navigation: phone tab bar, web header, footer and role sidebars; Console data table | Q91: Campus never sees an individual’s health data. | R91: To do
A92: SK-091 | B92: E9 · Campus admin console | C92: Students roster, CSV import and verification queue | D92: Story | E92: Web | F92: CampusRoster, CampusApprovals | G92: 4 · Campus / hostel admin | H92: 2 | I92: P0 | J92: 1 · Launch | K92: 8 | L92: Student list with enrolment status, CSV import of the roll list, and the college-ID verification queue. | M92: • Four verification dots per student, never documents • CSV import validates and previews before saving | N92: SK-019 | O92: Console data table | P92: Roster + verification queue | R92: To do
A93: SK-092 | B93: E9 · Campus admin console | C93: Health camps | D93: Story | E93: Web | F93: CampusCamps | G93: 4 · Campus / hostel admin | H93: 2 | I93: P1 | J93: 2 · Launch month | K93: 5 | L93: Plan and run health camps with partners. | M93: • Slots, partner, location • Bookings count only | N93: SK-090 | O93: Campus console home and overview | R93: To do
A94: SK-093 | B94: E9 · Campus admin console | C94: Health insights (aggregate) | D94: Story | E94: Web | F94: CampusInsights | G94: 4 · Campus / hostel admin | H94: 1 | I94: P1 | J94: 2 · Launch month | K94: 5 | L94: Anonymous campus-level trends. | M94: • Minimum group of 20; smaller groups hidden • Never mental or sexual health | N94: SK-090 | O94: Campus console home and overview | R94: To do
A95: SK-094 | B95: E9 · Campus admin console | C95: Access requests and emergency (break-glass) access | D95: Story | E95: Web | F95: CampusAccessRequests, CampusBreakGlass | G95: 4 · Campus / hostel admin | H95: 1 | I95: P0 | J95: 1 · Launch | K95: 8 | L95: Staff request access to a student’s record; break-glass for emergencies with reason and audit. | M95: • Break-glass needs reason + second person • Student is told afterwards • Every access logged | N95: SK-090 | O95: Campus console home and overview | P95: Access requests + audit log | R95: To do
A96: SK-095 | B96: E9 · Campus admin console | C96: Incident desk and counsellor queue | D96: Story | E96: Web | F96: CampusIncidents, CampusCounsellor | G96: 4 · Campus / hostel admin | H96: 1 | I96: P0 | J96: 1 · Launch | K96: 8 | L96: SOS and incident handling for campus responders; counsellor booking queue. | M96: • SLA timers • Counsellor queue never visible to general admins | N96: SK-052 | O96: SOS beacon and after-SOS | P96: Incidents + counselling bookings | R96: To do
A97: SK-096 | B97: E9 · Campus admin console | C97: Admin team and roles | D97: Story | E97: Web | F97: CampusAdminTeam | G97: 4 · Campus / hostel admin | H97: 3 | I97: P0 | J97: 1 · Launch | K97: 3 | L97: Invite admins and assign roles. | M97: • Removal signs out immediately • Role changes logged | N97: SK-090 | O97: Campus console home and overview | R97: To do
A98: SK-097 | B98: E9 · Campus admin console | C98: Isolation and discharge certificates | D98: Story | E98: Web | F98: CampusIsolation, CampusDischarge | G98: 4 · Campus / hostel admin | H98: 1 | I98: P1 | J98: 2 · Launch month | K98: 5 | L98: Track students in isolation rooms and issue discharge/fitness certificates. | M98: • Only what the student consented to share • Certificates signed by a clinician | N98: SK-090 | O98: Campus console home and overview | R98: To do
A99: SK-098 | B99: E9 · Campus admin console | C99: Outbreak, water and sanitary radars | D99: Story | E99: Web | F99: CampusOutbreak, CampusWater, CampusSanitary | G99: 4 · Campus / hostel admin | H99: 2 | I99: P2 | J99: 3 · Later | K99: 8 | L99: Early-warning dashboards from aggregate symptom reports, water tests and sanitary audits. | M99: • Aggregate only • Clear source and date on every number | N99: SK-093 | O99: Health insights (aggregate) | R99: To do
A100: SK-099 | B100: E9 · Campus admin console | C100: Mess and diet | D100: Story | E100: Web | F100: CampusMess | G100: 4 · Campus / hostel admin | H100: 3 | I100: P2 | J100: 3 · Later | K100: 3 | L100: Special diet requests and mess hygiene checks. | M100: • Diet requests without diagnosis details | N100: SK-090 | O100: Campus console home and overview | R100: To do
A101: SK-100 | B101: E9 · Campus admin console | C101: Ambulance dispatch and SLA escalation | D101: Story | E101: Web | F101: CampusAmbulance, CampusSla | G101: 4 · Campus / hostel admin | H101: 1 | I101: P1 | J101: 2 · Launch month | K101: 5 | L101: Dispatch an ambulance and escalate when response targets are missed. | M101: • Timers and escalation chain • Works with SOS incidents | N101: SK-095 | O101: Incident desk and counsellor queue | R101: To do
A102: SK-101 | B102: E9 · Campus admin console | C102: Hostel blocks | D102: Story | E102: Web | F102: CampusBlocks | G102: 4 · Campus / hostel admin | H102: 3 | I102: P1 | J102: 2 · Launch month | K102: 3 | L102: Blocks, rooms and wardens for delivery and visits. | M102: • CSV import • Used by delivery addresses | N102: SK-090 | O102: Campus console home and overview | R102: To do
A103: SK-102 | B103: E9 · Campus admin console | C103: Wellness workshops and announcements | D103: Story | E103: Web | F103: CampusWellness, CampusAnnouncements | G103: 4 · Campus / hostel admin | H103: 3 | I103: P2 | J103: 3 · Later | K103: 5 | L103: Schedule workshops and send announcements. | M103: • Announcements never target by health data | N103: SK-090 | O103: Campus console home and overview | R103: To do
...

Sheet Epics
A1: Epic | B1: Tickets | C1: Points | D1: P0 | E1: P1 | F1: P2 | G1: Done | H1: % done
A2: E0 · Launch blockers | B2: =COUNTIF(Tickets!$B$2:$B$148,A2) -> 6 | C2: =SUMIF(Tickets!$B$2:$B$148,A2,Tickets!$K$2:$K$148) -> 16 | D2: =COUNTIFS(Tickets!$B$2:$B$148,A2,Tickets!$I$2:$I$148,"P0") -> 6 | E2: =COUNTIFS(Tickets!$B$2:$B$148,A2,Tickets!$I$2:$I$148,"P1") -> 0 | F2: =COUNTIFS(Tickets!$B$2:$B$148,A2,Tickets!$I$2:$I$148,"P2") -> 0 | G2: =COUNTIFS(Tickets!$B$2:$B$148,A2,Tickets!$R$2:$R$148,"Done") -> 0 | H2: =IF(B2=0,0,G2/B2) -> 0
A3: E1 · Design system foundations | B3: =COUNTIF(Tickets!$B$2:$B$148,A3) -> 16 | C3: =SUMIF(Tickets!$B$2:$B$148,A3,Tickets!$K$2:$K$148) -> 72 | D3: =COUNTIFS(Tickets!$B$2:$B$148,A3,Tickets!$I$2:$I$148,"P0") -> 11 | E3: =COUNTIFS(Tickets!$B$2:$B$148,A3,Tickets!$I$2:$I$148,"P1") -> 5 | F3: =COUNTIFS(Tickets!$B$2:$B$148,A3,Tickets!$I$2:$I$148,"P2") -> 0 | G3: =COUNTIFS(Tickets!$B$2:$B$148,A3,Tickets!$R$2:$R$148,"Done") -> 0 | H3: =IF(B3=0,0,G3/B3) -> 0
A4: E2 · Launch, sign-in & onboarding | B4: =COUNTIF(Tickets!$B$2:$B$148,A4) -> 11 | C4: =SUMIF(Tickets!$B$2:$B$148,A4,Tickets!$K$2:$K$148) -> 58 | D4: =COUNTIFS(Tickets!$B$2:$B$148,A4,Tickets!$I$2:$I$148,"P0") -> 7 | E4: =COUNTIFS(Tickets!$B$2:$B$148,A4,Tickets!$I$2:$I$148,"P1") -> 4 | F4: =COUNTIFS(Tickets!$B$2:$B$148,A4,Tickets!$I$2:$I$148,"P2") -> 0 | G4: =COUNTIFS(Tickets!$B$2:$B$148,A4,Tickets!$R$2:$R$148,"Done") -> 0 | H4: =IF(B4=0,0,G4/B4) -> 0
A5: E3 · Student app — home, search & care | B5: =COUNTIF(Tickets!$B$2:$B$148,A5) -> 16 | C5: =SUMIF(Tickets!$B$2:$B$148,A5,Tickets!$K$2:$K$148) -> 92 | D5: =COUNTIFS(Tickets!$B$2:$B$148,A5,Tickets!$I$2:$I$148,"P0") -> 9 | E5: =COUNTIFS(Tickets!$B$2:$B$148,A5,Tickets!$I$2:$I$148,"P1") -> 5 | F5: =COUNTIFS(Tickets!$B$2:$B$148,A5,Tickets!$I$2:$I$148,"P2") -> 2 | G5: =COUNTIFS(Tickets!$B$2:$B$148,A5,Tickets!$R$2:$R$148,"Done") -> 0 | H5: =IF(B5=0,0,G5/B5) -> 0
A6: E4 · Student safety & privacy | B6: =COUNTIF(Tickets!$B$2:$B$148,A6) -> 12 | C6: =SUMIF(Tickets!$B$2:$B$148,A6,Tickets!$K$2:$K$148) -> 59 | D6: =COUNTIFS(Tickets!$B$2:$B$148,A6,Tickets!$I$2:$I$148,"P0") -> 7 | E6: =COUNTIFS(Tickets!$B$2:$B$148,A6,Tickets!$I$2:$I$148,"P1") -> 4 | F6: =COUNTIFS(Tickets!$B$2:$B$148,A6,Tickets!$I$2:$I$148,"P2") -> 1 | G6: =COUNTIFS(Tickets!$B$2:$B$148,A6,Tickets!$R$2:$R$148,"Done") -> 0 | H6: =IF(B6=0,0,G6/B6) -> 0
A7: E5 · Student app — shop & orders | B7: =COUNTIF(Tickets!$B$2:$B$148,A7) -> 6 | C7: =SUMIF(Tickets!$B$2:$B$148,A7,Tickets!$K$2:$K$148) -> 33 | D7: =COUNTIFS(Tickets!$B$2:$B$148,A7,Tickets!$I$2:$I$148,"P0") -> 4 | E7: =COUNTIFS(Tickets!$B$2:$B$148,A7,Tickets!$I$2:$I$148,"P1") -> 2 | F7: =COUNTIFS(Tickets!$B$2:$B$148,A7,Tickets!$I$2:$I$148,"P2") -> 0 | G7: =COUNTIFS(Tickets!$B$2:$B$148,A7,Tickets!$R$2:$R$148,"Done") -> 0 | H7: =IF(B7=0,0,G7/B7) -> 0
A8: E6 · Student app — account | B8: =COUNTIF(Tickets!$B$2:$B$148,A8) -> 5 | C8: =SUMIF(Tickets!$B$2:$B$148,A8,Tickets!$K$2:$K$148) -> 21 | D8: =COUNTIFS(Tickets!$B$2:$B$148,A8,Tickets!$I$2:$I$148,"P0") -> 3 | E8: =COUNTIFS(Tickets!$B$2:$B$148,A8,Tickets!$I$2:$I$148,"P1") -> 1 | F8: =COUNTIFS(Tickets!$B$2:$B$148,A8,Tickets!$I$2:$I$148,"P2") -> 1 | G8: =COUNTIFS(Tickets!$B$2:$B$148,A8,Tickets!$R$2:$R$148,"Done") -> 0 | H8: =IF(B8=0,0,G8/B8) -> 0
A9: E7 · Public website | B9: =COUNTIF(Tickets!$B$2:$B$148,A9) -> 6 | C9: =SUMIF(Tickets!$B$2:$B$148,A9,Tickets!$K$2:$K$148) -> 42 | D9: =COUNTIFS(Tickets!$B$2:$B$148,A9,Tickets!$I$2:$I$148,"P0") -> 4 | E9: =COUNTIFS(Tickets!$B$2:$B$148,A9,Tickets!$I$2:$I$148,"P1") -> 2 | F9: =COUNTIFS(Tickets!$B$2:$B$148,A9,Tickets!$I$2:$I$148,"P2") -> 0 | G9: =COUNTIFS(Tickets!$B$2:$B$148,A9,Tickets!$R$2:$R$148,"Done") -> 0 | H9: =IF(B9=0,0,G9/B9) -> 0
A10: E8 · Student web — signed in | B10: =COUNTIF(Tickets!$B$2:$B$148,A10) -> 11 | C10: =SUMIF(Tickets!$B$2:$B$148,A10,Tickets!$K$2:$K$148) -> 74 | D10: =COUNTIFS(Tickets!$B$2:$B$148,A10,Tickets!$I$2:$I$148,"P0") -> 10 | E10: =COUNTIFS(Tickets!$B$2:$B$148,A10,Tickets!$I$2:$I$148,"P1") -> 1 | F10: =COUNTIFS(Tickets!$B$2:$B$148,A10,Tickets!$I$2:$I$148,"P2") -> 0 | G10: =COUNTIFS(Tickets!$B$2:$B$148,A10,Tickets!$R$2:$R$148,"Done") -> 0 | H10: =IF(B10=0,0,G10/B10) -> 0
A11: E9 · Campus admin console | B11: =COUNTIF(Tickets!$B$2:$B$148,A11) -> 15 | C11: =SUMIF(Tickets!$B$2:$B$148,A11,Tickets!$K$2:$K$148) -> 81 | D11: =COUNTIFS(Tickets!$B$2:$B$148,A11,Tickets!$I$2:$I$148,"P0") -> 5 | E11: =COUNTIFS(Tickets!$B$2:$B$148,A11,Tickets!$I$2:$I$148,"P1") -> 7 | F11: =COUNTIFS(Tickets!$B$2:$B$148,A11,Tickets!$I$2:$I$148,"P2") -> 3 | G11: =COUNTIFS(Tickets!$B$2:$B$148,A11,Tickets!$R$2:$R$148,"Done") -> 0 | H11: =IF(B11=0,0,G11/B11) -> 0
A12: E10 · Doctor console | B12: =COUNTIF(Tickets!$B$2:$B$148,A12) -> 10 | C12: =SUMIF(Tickets!$B$2:$B$148,A12,Tickets!$K$2:$K$148) -> 57 | D12: =COUNTIFS(Tickets!$B$2:$B$148,A12,Tickets!$I$2:$I$148,"P0") -> 5 | E12: =COUNTIFS(Tickets!$B$2:$B$148,A12,Tickets!$I$2:$I$148,"P1") -> 3 | F12: =COUNTIFS(Tickets!$B$2:$B$148,A12,Tickets!$I$2:$I$148,"P2") -> 2 | G12: =COUNTIFS(Tickets!$B$2:$B$148,A12,Tickets!$R$2:$R$148,"Done") -> 0 | H12: =IF(B12=0,0,G12/B12) -> 0
A13: E11 · Partner console & staff app | B13: =COUNTIF(Tickets!$B$2:$B$148,A13) -> 13 | C13: =SUMIF(Tickets!$B$2:$B$148,A13,Tickets!$K$2:$K$148) -> 73 | D13: =COUNTIFS(Tickets!$B$2:$B$148,A13,Tickets!$I$2:$I$148,"P0") -> 8 | E13: =COUNTIFS(Tickets!$B$2:$B$148,A13,Tickets!$I$2:$I$148,"P1") -> 5 | F13: =COUNTIFS(Tickets!$B$2:$B$148,A13,Tickets!$I$2:$I$148,"P2") -> 0 | G13: =COUNTIFS(Tickets!$B$2:$B$148,A13,Tickets!$R$2:$R$148,"Done") -> 0 | H13: =IF(B13=0,0,G13/B13) -> 0
... A15: E13 · Quality & launch readiness | B15: =COUNTIF(Tickets!$B$2:$B$148,A15) -> 4 | C15: =SUMIF(Tickets!$B$2:$B$148,A15,Tickets!$K$2:$K$148) -> 21 | D15: =COUNTIFS(Tickets!$B$2:$B$148,A15,Tickets!$I$2:$I$148,"P0") -> 2 | E15: =COUNTIFS(Tickets!$B$2:$B$148,A15,Tickets!$I$2:$I$148,"P1") -> 2 | F15: =COUNTIFS(Tickets!$B$2:$B$148,A15,Tickets!$I$2:$I$148,"P2") -> 0 | G15: =COUNTIFS(Tickets!$B$2:$B$148,A15,Tickets!$R$2:$R$148,"Done") -> 0 | H15: =IF(B15=0,0,G15/B15) -> 0
A16: Total | B16: =SUM(B2:B15) -> 147 | C16: =SUM(C2:C15) -> 785 | D16: =SUM(D2:D15) -> 90 | E16: =SUM(E2:E15) -> 46 | F16: =SUM(F2:F15) -> 11 | G16: =SUM(G2:G15) -> 0 | H16: =IF(B16=0,0,G16/B16) -> 0

Sheet Screens
A1: Canvas page | B1: Screen | C1: Title on canvas | D1: Built in ticket(s)
A2: 1 · Launch & onboarding | B2: WebSignOut | D2: SK-079
A3: 1 · Launch & onboarding | B3: Main | C3: Splash — changes with the time of day (morning · afternoon · evening) | D3: SK-023
A4: 1 · Launch & onboarding | B4: SplashPulse | C4: Splash variant — afternoon (heartbeat) | D4: SK-023
A5: 1 · Launch & onboarding | B5: SplashVault | C5: Splash variant — evening (care circle) | D5: SK-023
A6: 1 · Launch & onboarding | B6: Onboarding1 | C6: Onboarding 1 — Campus care | D6: SK-024
A7: 1 · Launch & onboarding | B7: Onboarding2 | C7: Onboarding 2 — Health vault | D7: SK-024
A8: 1 · Launch & onboarding | B8: Onboarding3 | C8: Onboarding 3 — Ayush AI | D8: SK-024
A9: 1 · Launch & onboarding | B9: SignIn | C9: Sign in | D9: SK-003, SK-010, SK-021, SK-025
A10: 1 · Launch & onboarding | B10: OtpVerify | C10: OTP verification | D10: SK-003, SK-010, SK-025
A11: 1 · Launch & onboarding | B11: CreateAccount | C11: Create account — step 1 | D11: SK-010, SK-026
A12: 1 · Launch & onboarding | B12: CampusVerify | C12: Campus verify — step 2 | D12: SK-026
A13: 1 · Launch & onboarding | B13: ProfileSetup | C13: Care profile — step 3 | D13: SK-026
A14: 1 · Launch & onboarding | B14: Permissions | C14: Permissions — step 4 | D14: SK-011, SK-026
... A240: 8 · Design system & flow map | B240: Feedback | C240: System — feedback (toasts, banners, validation) | D240: SK-010, SK-012, SK-013
